apt_smart/__init__.py
apt_smart/cli.py
apt_smart/http.py
apt_smart/releases.py
apt_smart/tests.py
apt_smart/backends/__init__.py
apt_smart/backends/debian.py
apt_smart/backends/linuxmint.py
apt_smart/backends/ubuntu.py
apt_smart-7.1.3.dist-info/LICENSE.txt
apt_smart-7.1.3.dist-info/METADATA
apt_smart-7.1.3.dist-info/WHEEL
apt_smart-7.1.3.dist-info/entry_points.txt
apt_smart-7.1.3.dist-info/top_level.txt
apt_smart-7.1.3.dist-info/RECORD
