Metadata-Version: 2.1
Name: apt-smart
Version: 7.1.3
Summary: Automated, robust apt-get mirror selection for Debian and Ubuntu
Home-page: https://apt-smart.readthedocs.io
Author: martin68
Author-email: 
License: MIT
Platform: UNKNOWN
Classifier: Development Status :: 4 - Beta
Classifier: Environment :: Console
Classifier: Intended Audience :: Developers
Classifier: Intended Audience :: Information Technology
Classifier: Intended Audience :: System Administrators
Classifier: License :: OSI Approved :: MIT License
Classifier: Natural Language :: English
Classifier: Operating System :: POSIX :: Linux
Classifier: Programming Language :: Python
Classifier: Programming Language :: Python :: 2
Classifier: Programming Language :: Python :: 2.7
Classifier: Programming Language :: Python :: 3
Classifier: Programming Language :: Python :: 3.4
Classifier: Programming Language :: Python :: 3.5
Classifier: Programming Language :: Python :: 3.6
Classifier: Programming Language :: Python :: 3.7
Classifier: Programming Language :: Python :: 3.8
Classifier: Programming Language :: Python :: Implementation :: CPython
Classifier: Programming Language :: Python :: Implementation :: PyPy
Classifier: Topic :: Software Development
Classifier: Topic :: Software Development :: Libraries :: Python Modules
Classifier: Topic :: System :: Shells
Classifier: Topic :: System :: System Shells
Classifier: Topic :: System :: Systems Administration
Classifier: Topic :: Terminals
Classifier: Topic :: Utilities
Requires-Dist: beautifulsoup4 (>=4.4.1)
Requires-Dist: capturer (>=2.1.1)
Requires-Dist: coloredlogs (>=5.0)
Requires-Dist: executor (>=21.1.1)
Requires-Dist: humanfriendly (>=4.17)
Requires-Dist: six (>=1.10.0)
Requires-Dist: stopit (>=1.1.1)
Requires-Dist: wheel (>=0.26.0)
Requires-Dist: property-manager (>=1.3) ; python_version < "3.3"
Requires-Dist: flufl.enum (<4.1,>=4.0.1) ; python_version == "2.6"
Requires-Dist: flufl.enum (>=4.0.1) ; python_version == "2.6" or python_version == "2.7" or python_version == "3.0" or python_version == "3.1" or python_version == "3.2" or python_version == "3.3"
Requires-Dist: property-manager3 ; python_version >= "3.3"
